vloginit/__init__.py
vloginit/__main__.py
vloginit/main.py
vloginit/vlog.py
vloginit-0.0.3.dist-info/LICENSE
vloginit-0.0.3.dist-info/METADATA
vloginit-0.0.3.dist-info/WHEEL
vloginit-0.0.3.dist-info/entry_points.txt
vloginit-0.0.3.dist-info/top_level.txt
vloginit-0.0.3.dist-info/RECORD
