Metadata-Version: 2.1
Name: vloginit
Version: 0.0.3
Summary: Simple script for verilog/systemverilog module templates generation
Home-page: https://gitlab.com/vborshch/vloginit
Author: Vladislav Borshch, Shekhalev Denis
Author-email: borchsh.vn@mail.com, diod2003@list.ru
License: MIT
Project-URL: Bug Tracker, https://gitlab.com/vborshch/vloginit/issues
Platform: UNKNOWN
Classifier: Programming Language :: Python :: 3
Classifier: License :: OSI Approved :: MIT License
Classifier: Operating System :: OS Independent
Requires-Python: >=3.6
License-File: LICENSE
